mdfm/__init__.py
mdfm/__main__.py
mdfm/_version.py
mdfm/mdfm.py
mdfm-0.0.2.dist-info/LICENSE
mdfm-0.0.2.dist-info/METADATA
mdfm-0.0.2.dist-info/WHEEL
mdfm-0.0.2.dist-info/entry_points.txt
mdfm-0.0.2.dist-info/top_level.txt
mdfm-0.0.2.dist-info/RECORD
