Metadata-Version: 2.1
Name: mdfm
Version: 0.0.2
Summary: mdfm is a linux tools for My Dot Files Manager. (backup or restore)
Home-page: http://github.com/lisuke/mdfm
Author: lisuke
Author-email: 1657787678@qq.com
License: GPLv3
Keywords: dfm,mdfm,dotfiles,backup,backup-script,linux,python
Platform: any
Requires-Python: >=3
License-File: LICENSE
Requires-Dist: pathlib
Requires-Dist: argparse
Requires-Dist: termcolor
